cvo251203app/__init__.py
cvo251203app/__main__.py
cvo251203app/cvo251203app.py
cvo251203app/py.typed
cvo251203app-0.2.0.dist-info/WHEEL
cvo251203app-0.2.0.dist-info/entry_points.txt
cvo251203app-0.2.0.dist-info/METADATA
cvo251203app-0.2.0.dist-info/RECORD
